model_factory/__init__.py
model_factory/cli.py
model_factory/layers_manager.py
model_factory/model_factory.py
model_factory/layers/__init__.py
model_factory/layers/attentions/__init__.py
model_factory/layers/attentions/multihead_attention.py
model_factory/layers/embeddings/__init__.py
model_factory/layers/embeddings/pos_embedding.py
model_factory/layers/recurrents/__init__.py
model_factory/layers/recurrents/rnns.py
model_factory/layers/transformers/__init__.py
model_factory/layers/transformers/bert.py
model_factory/layers/transformers/longformer.py
model_factory/layers/transformers/reformer.py
model_factory/layers/transformers/transformer.py
model_factory/layers/transformers/transformer_xl.py
model_factory/losses/__init__.py
model_factory/losses/loss.py
model_factory/models/__init__.py
model_factory/models/classifier_model.py
model_factory/models/gan_model.py
model_factory/models/model.py
model_factory/models/rl_model.py
model_factory/models/seq2seq_model.py
model_factory/models/seqlabel_model.py
model_factory/utils/__init__.py
model_factory/utils/activations.py
model_factory/utils/common_struct.py
model_factory/utils/serialize.py
model_factory-0.0.8.dist-info/AUTHORS.rst
model_factory-0.0.8.dist-info/LICENSE
model_factory-0.0.8.dist-info/METADATA
model_factory-0.0.8.dist-info/WHEEL
model_factory-0.0.8.dist-info/entry_points.txt
model_factory-0.0.8.dist-info/top_level.txt
model_factory-0.0.8.dist-info/RECORD
