Metadata-Version: 2.1
Name: model-factory
Version: 0.0.8
Summary: machine learning model collections and maquiladora
Home-page: https://github.com/yinochaos/model_factory
Author: yinochaos
Author-email: pspcxl@163.com
License: Apache Software License 2.0
Keywords: model_factory
Platform: UNKNOWN
Classifier: Development Status :: 2 - Pre-Alpha
Classifier: Intended Audience :: Developers
Classifier: License :: OSI Approved :: Apache Software License
Classifier: Natural Language :: English
Classifier: Programming Language :: Python :: 3.6
Classifier: Programming Language :: Python :: 3.7
Classifier: Programming Language :: Python :: 3.8
Requires-Python: >=3.5
